{
    "name": "apidoc spec",
    "description": "Specification of apidoc api.json schema",
    "base_url": "http://api.apidoc.me",

    "enums": {
	"method": {
	    "values": [
		{ "name": "GET" },
		{ "name": "POST" },
		{ "name": "PUT" },
		{ "name": "PATCH" },
		{ "name": "DELETE" },
		{ "name": "HEAD" },
		{ "name": "CONNECT" },
		{ "name": "OPTIONS" },
		{ "name": "TRACE" }
	    ]
	},

	"parameter_location": {
	    "values": [
		{ "name": "Path" },
		{ "name": "Query" },
		{ "name": "Form" }
	    ]
	}
    },

    "models": {
	"service": {
	    "fields": [
		{ "name": "name", "type": "string" },
		{ "name": "key", "type": "string", "description": "Unique key to identify this service. URL friendly" },
		{ "name": "namespace", "type": "string", "description": "Fully qualified namespace for this service - e.g. com.gilt.apidoc." },
		{ "name": "version", "type": "string", "example": "1.0.0" },
		{ "name": "base_url", "type": "string", "required": false },
		{ "name": "description", "type": "string", "required": false },
		{ "name": "headers", "type": "[header]" },
		{ "name": "imports", "type": "[import]" },
		{ "name": "enums", "type": "[enum]" },
		{ "name": "models", "type": "[model]" },
		{ "name": "resources", "type": "[resource]", "description": "keys are the names of a model" }
	    ]
	},

	"enum": {
	    "fields": [
		{ "name": "name", "type": "string" },
		{ "name": "description", "type": "string", "required": false },
		{ "name": "values", "type": "[enum_value]" }
	    ]
	},

	"enum_value": {
	    "fields": [
		{ "name": "name", "type": "string" },
		{ "name": "description", "type": "string", "required": false }
	    ]
	},

	"model": {
	    "fields": [
		{ "name": "name", "type": "string" },
		{ "name": "plural", "type": "string" },
		{ "name": "description", "type": "string", "required": false },
		{ "name": "fields", "type": "[field]" }
	    ]
	},

	"field": {
	    "fields": [
		{ "name": "name", "type": "string" },
		{ "name": "type", "type": "string" },
		{ "name": "description", "type": "string", "required": false },
		{ "name": "default", "type": "string", "required": false },
		{ "name": "required", "type": "boolean" },
		{ "name": "minimum", "type": "long", "required": false },
		{ "name": "maximum", "type": "long", "required": false },
		{ "name": "example", "type": "string", "required": false }
	    ]
	},

	"resource": {
	    "fields": [
		{ "name": "model", "type": "model" },
		{ "name": "description", "type": "string", "required": false },
		{ "name": "operations", "type": "[operation]" }
	    ]
	},

	"operation": {
	    "fields": [
		{ "name": "method", "type": "method" },
		{ "name": "path", "type": "string" },
		{ "name": "description", "type": "string", "required": false },
		{ "name": "body", "type": "body", "required": false },
		{ "name": "parameters", "type": "[parameter]", "required": false },
		{ "name": "responses", "type": "[response]", "required": false }
	    ]
	},

	"body": {
	    "fields": [
		{ "name": "type", "type": "string" },
		{ "name": "description", "type": "string", "required": false }
	    ]
	},

	"parameter": {
	    "fields": [
		{ "name": "name", "type": "string" },
		{ "name": "type", "type": "string" },
		{ "name": "location", "type": "parameter_location" },
		{ "name": "description", "type": "string", "required": false },
		{ "name": "required", "type": "boolean" },
		{ "name": "default", "type": "string", "required": false },
		{ "name": "minimum", "type": "long", "required": false },
		{ "name": "maximum", "type": "long", "required": false },
		{ "name": "example", "type": "string", "required": false }
	    ]
	},

	"response": {
	    "fields": [
		{ "name": "code", "type": "integer" },
		{ "name": "type", "type": "string" }
	    ]
	},

	"header": {
	    "fields": [
		{ "name": "name", "type": "string" },
		{ "name": "type", "type": "string" },
		{ "name": "description", "type": "string", "required": false },
		{ "name": "required", "type": "boolean" },
		{ "name": "default", "type": "string", "required": false }
	    ]
	},

	"import": {
	    "description": "An import is used to declare a dependency on another service. This allows you to reference the models and or enums from that service in your own service.",
	    "fields": [
		{ "name": "uri", "type": "string", "description": "Full URI to the service.json file of the service we are importing", "example": "http://www.apidoc.me/gilt/apidoc-spec/0.7.38/service.json"  },
		{ "name": "namespace", "type": "string", "description": "the fully qualified namespace that we have imported", "example": "com.gilt.apidoc" },
		{ "name": "organization_key", "type": "string", "description": "The apidoc organization key to which this imported service belongs", "example": "gilt" },
		{ "name": "application_key", "type": "string", "description": "The apidoc application key to which this imported service belongs", "example": "apidoc" },
		{ "name": "version", "type": "string", "description": "The version of the service that we are importing", "example": "1.0.0" }
	    ]
	}

    }

}
